fork2gitlab/__init__.py
fork2gitlab/commands/ForkCommand.py
fork2gitlab/commands/SyncCommand.py
fork2gitlab/commands/__init__.py
fork2gitlab/git.py
fork2gitlab/main.py
fork2gitlab/utils.py
fork2gitlab-0.2.4.dist-info/LICENSE
fork2gitlab-0.2.4.dist-info/METADATA
fork2gitlab-0.2.4.dist-info/WHEEL
fork2gitlab-0.2.4.dist-info/entry_points.txt
fork2gitlab-0.2.4.dist-info/RECORD
