Metadata-Version: 2.1
Name: fork2gitlab
Version: 0.2.4
Summary: A script to help forking a project to gitlab and keeping it updated downstream
Home-page: https://gitlab.com/NamingThingsIsHard/collaboration/fork2gitlab
License: GPL-3.0-or-later
Keywords: cron,forking,gitlab,script
Author: LoveIsGrief
Author-email: loveisgrief@tuta.io
Requires-Python: >=3.7,<4.0
Classifier: Development Status :: 3 - Alpha
Classifier: License :: OSI Approved :: GNU General Public License v3 or later (GPLv3+)
Classifier: Operating System :: POSIX
Classifier: Programming Language :: Python :: 3
Classifier: Programming Language :: Python :: 3.7
Classifier: Programming Language :: Python :: 3.8
Classifier: Programming Language :: Python :: 3.9
Classifier: Programming Language :: Python :: 3.10
Classifier: Programming Language :: Python :: 3.11
Classifier: Programming Language :: Python :: 3.12
Classifier: Topic :: Software Development :: Version Control :: Git
Requires-Dist: cliff (>=3.1.0,<4.0.0)
Requires-Dist: python-gitlab (>=3.15.0,<4.0.0)
Project-URL: Bug Tracker, https://gitlab.com/NamingThingsIsHard/collaboration/fork2gitlab/-/issues
Project-URL: Repository, https://gitlab.com/NamingThingsIsHard/collaboration/fork2gitlab
